Metadata-Version: 1.0
Name: gaussian-tool
Version: 1.1
Summary: Gaussian and Binomial distributions
Home-page: UNKNOWN
Author: Sarthak Sharma
Author-email: sarthakparashar1408@gmail.com
License: UNKNOWN
Platform: UNKNOWN
